actuallyslowargfast-0.1.1.data/scripts/reallyslowarg
actuallyslowargfast-0.1.1.dist-info/licenses/LICENSE
reallyslowarg/__init__.py
reallyslowarg/main.py
reallyslowarg/reallyslowarg_snapshot.json
actuallyslowargfast-0.1.1.dist-info/METADATA
actuallyslowargfast-0.1.1.dist-info/WHEEL
actuallyslowargfast-0.1.1.dist-info/top_level.txt
actuallyslowargfast-0.1.1.dist-info/RECORD
