Metadata-Version: 2.4
Name: actuallyslowargfast
Version: 0.1.1
Summary: A really slow CLI tool for testing tab completion with fastargsnap (fast version)
Author-email: Uday Ayya <uday.ayya@gmail.com>
License-Expression: MIT
Project-URL: Homepage, https://github.com/udayayya/actuallyslowargfast
Project-URL: Repository, https://github.com/udayayya/actuallyslowargfast
Project-URL: Issues, https://github.com/udayayya/actuallyslowargfast/issues
Keywords: cli,argparse,argcomplete,tab-completion,performance,fastargsnap,fast
Classifier: Development Status :: 3 - Alpha
Classifier: Intended Audience :: Developers
Classifier: Programming Language :: Python :: 3
Classifier: Programming Language :: Python :: 3.8
Classifier: Programming Language :: Python :: 3.9
Classifier: Programming Language :: Python :: 3.10
Classifier: Programming Language :: Python :: 3.11
Classifier: Programming Language :: Python :: 3.12
Classifier: Topic :: Software Development :: Libraries :: Python Modules
Classifier: Topic :: System :: Shells
Classifier: Topic :: Utilities
Requires-Python: >=3.8
License-File: LICENSE
Requires-Dist: argparse
Requires-Dist: argcomplete
Requires-Dist: matplotlib
Requires-Dist: numpy
Requires-Dist: pandas
Requires-Dist: scikit-learn
Requires-Dist: requests
Requires-Dist: click
Requires-Dist: fastargsnap
Provides-Extra: dev
Requires-Dist: pytest; extra == "dev"
Requires-Dist: black; extra == "dev"
Requires-Dist: flake8; extra == "dev"
Dynamic: license-file
